LICENSE.txt
README.md
setup.py
HEAT_CF/HEAT_CF.py
HEAT_CF/__init__.py
HEAT_CF/dataDL.py
HEAT_CF/modelDL.py
HEAT_CF/plotting.py
HEAT_CF.egg-info/PKG-INFO
HEAT_CF.egg-info/SOURCES.txt
HEAT_CF.egg-info/dependency_links.txt
HEAT_CF.egg-info/top_level.txt