Metadata-Version: 2.1
Name: HEAT-CF
Version: 0.0.1
Summary: Inference of Heterogeneous perturbation Effects in single cell CRISPR screening data through Adversarial Training and Causal Forests
Author: ZichuFu
Author-email: 1779404540@qq.com
Platform: all
Classifier: Intended Audience :: Developers
Classifier: Operating System :: OS Independent
Classifier: Natural Language :: Chinese (Simplified)
Classifier: Programming Language :: Python
License-File: LICENSE.txt
